delugerpc/__init__.py
delugerpc/core.py
delugerpc/utils.py
delugerpc/__metadata__/LICENSE
delugerpc/__metadata__/README.md
delugerpc/__metadata__/__init__.py
delugerpc/__metadata__/requirements.txt
delugerpc-0.2.1.dist-info/METADATA
delugerpc-0.2.1.dist-info/WHEEL
delugerpc-0.2.1.dist-info/top_level.txt
delugerpc-0.2.1.dist-info/RECORD
